[
    {
        "id": "Gluem Portfolio",
        "introduction": "このWEBサイトです。「星の降る島」をイメージした背景の上に、各コンテンツを配置しています。",
        "thumbnail": "img/application/PortfolioThum.png",
        "points": [
            {
                "title": "3D空間の描画による、立体感のあるWEBサイト",
                "texts": [
                    "TresJSでの3D空間の描画とOrbitControlsによるカメラの制御により、ドラッグ操作にて3D空間の視点を変更できます。",
                    "👉TresJS",
                    "　Three.jsの各機能をVue.jsのコンポーネントと同様に扱えるライブラリ",
                    "👉Three.js",
                    "　HTML5上で3Dコンテンツを制作するためのJavaScriptライブラリ",
                    "👉OrbitControls",
                    "　Three.js の機能の一つで、3D空間上のカメラの動きをマウスの操作と同期させる機能"
                ]
            },
            {
                "title": "3Dオブジェクトのアニメーション",
                "texts": [
                    "3D空間上に様々な色・形の星が降ってくる様子を描画し、幻想的な雰囲気にしています。",
                    "サイトのタイトルを3Dオブジェクトにして画面スクロールと同期させる事で、アニメーションを描画しています。"
                ]
            },
            {
                "title": "画面内の星をクリックすると！？",
                "texts": []
            }
        ],
        "screenShot": [
            "img/application/Portfolio1.png",
            "img/application/Portfolio2.png"
        ],
        "environment": [
            "Vue.js",
            "TypeScript",
            "TresJS",
            "Three.js"
        ],
        "tool": [
            "Visual Studio Code",
            "GitHub",
            "Figma"
        ],
        "url": "",
        "githubUrl": ""
    },
    {
        "id": "Seventh Dawn",
        "introduction": "ダンジョンを探索するRPGのSPAです。Vue.jsとThree.jsを組み合わせて作成しています。（永遠のα版）",
        "thumbnail": "img/application/SeventhThum.png",
        "points": [
            {
                "title": "入るたびにランダムに構成される3Dダンジョン",
                "texts": [
                    "ダンジョンは自動生成アルゴリズムにより、ダンジョン情報（大きさ、部屋の大きさ、部屋の数、通路の集合地点など）から、毎回ランダムな構造のダンジョンを生成します。"
                ]
            },
            {
                "title": "Three.jsで構築した3Dダンジョンの探索",
                "texts": [
                    "ダンジョンはThree.jsにて3D空間上に描画し、各ダンジョンはダンジョン名に沿って異なるテクスチャーや音楽を設定しています。",
                    "また、ダンジョン内はカメラ（プレイヤー）の動きに合わせて探索する事が可能で、扉や宝箱などのオブジェクトも操作可能です。"
                ]
            },
            {
                "title": "非同期処理による戦闘中のスムーズなアニメーション",
                "texts": [
                    "戦闘中のコマンド入力やアニメーションに関して、非同期処理やタイマー処理を組み合わせる事で、出来るだけストレスなくスムーズに動くようにしています。"
                ]
            },
            {
                "title": "シンプルかつ拡張性のあるデータの持ち方",
                "texts": [
                    "キャラクターや装備等の殆どのデータはjson形式で保持しており、各クラスに格納する事で、データに関する処理をシンプルにしています。"
                ]
            },
            {
                "title": "ストア機能によるアプリ全体のデータ管理",
                "texts": [
                    "アプリ内で共有するデータはpiniaによるストア機能で管理しています。",
                    "これにより、アプリ内のどこからでも共有データの参照・更新をシンプルに行っています。"
                ]
            }
        ],
        "screenShot": [
            "img/application/SeventhDawn1.png",
            "img/application/SeventhDawn2.png",
            "img/application/SeventhDawn3.gif",
            "img/application/SeventhDawn4.png"
        ],
        "environment": [
            "Vue.js",
            "TypeScript",
            "Three.js",
            "animejs",
            "pinia"
        ],
        "tool": [
            "Visual Studio Code",
            "GitHub",
            "Figma",
            "MediBang Paint Pro",
            "Blender"
        ],
        "url": "https://gluem0418.github.io/SeventhDawn/",
        "githubUrl": ""
    },
    {
        "id": "Web Detection",
        "introduction": "AIによるObject Detection（物体検出）の学習済みモデルを使用し、任意の画像内に存在するモノを判別するアプリケーションです。",
        "thumbnail": "img/application/DectThum.png",
        "points": [
            {
                "title": "Object Detectionの学習済みモデルによる物体検出",
                "texts": [
                    "選択した画像を解析用のフォーマットに変換し、Object Detectionの学習済みモデルで解析する事で画像内に存在するモノを検出してます。",
                    "解析後の画像は通常のフォーマットに戻し、検出結果と併せて画面に表示しています。",
                    "また、解析後の画像の検出結果をクリックすると、検出結果を音声で再生します。"
                ]
            },
            {
                "title": "Ajaxによる処理毎のデータ更新",
                "texts": [
                    "モデルのロード処理と画像の検索処理はそれぞれAjaxにてデータを取得しています。",
                    "各処理を並行で進める事により、準備にかかる時間を短縮できるようにしています。"
                ]
            }
        ],
        "screenShot": [
            "img/application/Dect1.png",
            "img/application/Dect2.png"
        ],
        "environment": [
            "Python",
            "Flask",
            "JavaScript",
            "Ajax"
        ],
        "tool": [
            "Visual Studio Code",
            "PythonAnywhere",
            "Figma"
        ],
        "url": "https://gluem0418.github.io/SeventhDawn/",
        "githubUrl": ""
    },
    {
        "id": "Starry Island",
        "introduction": "このWEBサイトの初期段階にて背景用に作成したコンテンツです。",
        "thumbnail": "img/application/starThum.png",
        "points": [
            {
                "title": "大量のオブジェクト（星）の一括操作",
                "texts": [
                    "すべての星をBufferGeometryで定義することで、8600個の星のアニメーションを効率良く処理出来るようにしています。",
                    "👉BufferGeometry",
                    "　オブジェクトの情報（頂点の位置、色など）をバッファ（型指定された配列）に格納しているので、GPUの負荷が軽減する"
                ]
            },
            {
                "title": "星の形のテクスチャーの反映",
                "texts": [
                    "ShaderMaterialとglslを使用することで、各星に星型のテクスチャーを反映しています。",
                    "👉ShaderMaterial",
                    "　任意のシェーダー（CGレンダリングをするプログラム）を組み込めるマテリアル",
                    "👉glsl",
                    "　3Dグラフィックスを作成するためのシェーディング言語"
                ]
            },
            {
                "title": "画面内のどこかをクリックすると！？",
                "texts": []
            }
        ],
        "screenShot": [
            "img/application/Star1.png",
            "img/application/Star2.png"
        ],
        "environment": [
            "Vue.js",
            "TypeScript",
            "TresJS",
            "Three.js"
        ],
        "tool": [
            "Visual Studio Code",
            "GitHub"
        ],
        "url": "https://gluem0418.github.io/stars1/",
        "githubUrl": "https://github.com/gluem0418/stars1"
    },
    {
        "id": "Whack-a-mole",
        "introduction": "シンプルなもぐら叩きです。昔バニラJSで作成したアプリをVue.js+TypeScriptに移行したものです。",
        "thumbnail": "img/application/WhackThum.png",
        "points": [
            {
                "title": "ステージを進む毎に難易度があがる構成",
                "texts": [
                    "モンスターを叩いてスコアが一定に達すると、ステージが変わって難易度が上がっていきます。"
                ]
            },
            {
                "title": "各アニメーション",
                "texts": [
                    "モンスターやハンマーの動きはanime.jsを使用して滑らかなアニメーションにしています。",
                    "また、モンスターを叩いた際には吹っ飛んでいく動きで爽快感を出すようにしています。"
                ]
            }
        ],
        "screenShot": [
            "img/application/Whack1.png",
            "img/application/Whack2.png"
        ],
        "environment": [
            "Vue.js",
            "TypeScript",
            "animejs"
        ],
        "tool": [
            "Visual Studio Code",
            "GitHub"
        ],
        "url": "https://gluem0418.github.io/ClickT/",
        "githubUrl": "https://github.com/gluem0418/ClickT"
    },
    {
        "id": "The End Of Fear",
        "introduction": "Vue.jsにて最初に作成したSPA、ホラー風味のノベルゲームです。突然見知らぬ場所に迷い込んだあなた、待ち受ける衝撃の結末とは。。。",
        "thumbnail": "img/application/FearThum.png",
        "points": [
            {
                "title": "シーン毎のストーリーの描写",
                "texts": [
                    "各シーンでのストーリーと音声・効果音をクリック毎にスムーズに表示する事で、よりリアルに物語に入れるようにしています。"
                ]
            },
            {
                "title": "ホラーシーンの描写",
                "texts": [
                    "anime.jsでモンスターにランダムな動きをつける事で、より不気味な印象を与えるようにしています。"
                ]
            }
        ],
        "screenShot": [
            "img/application/Fear1.png",
            "img/application/Fear2.png"
        ],
        "environment": [
            "Vue.js",
            "JavaScript",
            "animejs"
        ],
        "tool": [
            "Visual Studio Code",
            "GitHub"
        ],
        "url": "https://gluem0418.github.io/app1/",
        "githubUrl": "https://github.com/gluem0418/app1"
    }
]